sdbus_async/systemd/__init__.py
sdbus_async/systemd/interfaces.py
sdbus_async/systemd/objects.py
sdbus_async/systemd/py.typed
sdbus_block/systemd/__init__.py
sdbus_block/systemd/interfaces.py
sdbus_block/systemd/objects.py
sdbus_block/systemd/py.typed
sdbus_systemd-1.0.0.dist-info/COPYING.LESSER
sdbus_systemd-1.0.0.dist-info/METADATA
sdbus_systemd-1.0.0.dist-info/WHEEL
sdbus_systemd-1.0.0.dist-info/top_level.txt
sdbus_systemd-1.0.0.dist-info/RECORD
