Metadata-Version: 2.1
Name: sdbus-systemd
Version: 1.0.0
Summary: Systemd binds for sdbus.
Home-page: https://github.com/igo95862/python-sdbus
Author: Bernhard Kaindl
Author-email: contact@bernhard.kaindl.dev
License: LGPL-2.1-or-later
Project-URL: Documentation, https://python-sdbus-systemd.readthedocs.io/en/latest/
Project-URL: Source, https://github.com/bernhardkaindl/python-sdbus-systemd/
Project-URL: Tracker, https://github.com/bernhardkaindl/python-sdbus-systemd/issues/
Keywords: dbus systemd networking linux freedesktop
Classifier: Development Status :: 4 - Beta
Classifier: Intended Audience :: Developers
Classifier: License :: OSI Approved :: GNU Lesser General Public License v2 or later (LGPLv2+)
Classifier: Operating System :: POSIX :: Linux
Classifier: Programming Language :: Python :: 3 :: Only
Classifier: Topic :: Software Development :: Libraries :: Python Modules
Requires-Python: >=3.7
License-File: COPYING.LESSER
Requires-Dist: sdbus >=0.10.2
